ytpu/__init__.py
ytpu/downloader.py
ytpu/file_io.py
ytpu/main.py
ytpu-0.1.2.dist-info/entry_points.txt
ytpu-0.1.2.dist-info/licenses/LICENSE
ytpu-0.1.2.dist-info/WHEEL
ytpu-0.1.2.dist-info/METADATA
ytpu-0.1.2.dist-info/RECORD
