Metadata-Version: 2.4
Name: ytpu
Version: 0.1.2
Summary: YT-DLP Playlist Audio Downloaded
Keywords: downloader,video,media
Author: ritonun
Requires-Python: >=3.12
Classifier: Programming Language :: Python :: 3
Classifier: License :: OSI Approved :: MIT License
Classifier: Operating System :: OS Independent
License-File: LICENSE
Requires-Dist: pathvalidate==3.3.1
Requires-Dist: tqdm==4.67.1
